transpose/__init__.py
transpose/__main__.py
transpose/extras/__init__.py
transpose/extras/plot.py
transpose/models/__init__.py
transpose/src/__init__.py
transpose/src/base.py
transpose/src/api/__init__.py
transpose/src/api/constants.py
transpose/src/api/analytical/__init__.py
transpose/src/api/analytical/base.py
transpose/src/api/block/__init__.py
transpose/src/api/block/_accounts_by_address.py
transpose/src/api/block/_accounts_by_date_created.py
transpose/src/api/block/_blocks_by_date.py
transpose/src/api/block/_blocks_by_number.py
transpose/src/api/block/_contracts_by_creator.py
transpose/src/api/block/_logs_by_block.py
transpose/src/api/block/_logs_by_transaction.py
transpose/src/api/block/_transactions_by_account.py
transpose/src/api/block/_transactions_by_block.py
transpose/src/api/block/_transactions_by_date.py
transpose/src/api/block/_transactions_by_hash.py
transpose/src/api/block/base.py
transpose/src/api/endpoint/__init__.py
transpose/src/api/endpoint/base.py
transpose/src/api/ens/__init__.py
transpose/src/api/ens/_records_by_account.py
transpose/src/api/ens/_records_by_date.py
transpose/src/api/ens/_records_by_name.py
transpose/src/api/ens/_records_by_owner.py
transpose/src/api/ens/_records_by_token_id.py
transpose/src/api/ens/_transfers_by_name.py
transpose/src/api/ens/_transfers_by_token_id.py
transpose/src/api/ens/base.py
transpose/src/api/nft/__init__.py
transpose/src/api/nft/_collections_by_contract_address.py
transpose/src/api/nft/_collections_by_date_created.py
transpose/src/api/nft/_collections_by_name.py
transpose/src/api/nft/_collections_by_symbol.py
transpose/src/api/nft/_nfts_by_contract_address.py
transpose/src/api/nft/_nfts_by_date_minted.py
transpose/src/api/nft/_nfts_by_name.py
transpose/src/api/nft/_nfts_by_owner.py
transpose/src/api/nft/_nfts_by_token_id.py
transpose/src/api/nft/_owners_by_contract_address.py
transpose/src/api/nft/_owners_by_token_id.py
transpose/src/api/nft/_sales.py
transpose/src/api/nft/_sales_by_account.py
transpose_data-4.2.2.dist-info/LICENSE
transpose_data-4.2.2.dist-info/METADATA
transpose_data-4.2.2.dist-info/WHEEL
transpose_data-4.2.2.dist-info/top_level.txt
transpose_data-4.2.2.dist-info/RECORD
