Metadata-Version: 2.1
Name: transpose-data
Version: 4.2.2
Summary: Web3 Data Made Simple. Powerful APIs for accessing human-readable blockchain data at scale: from blocks and transactions to NFTs and tokens.
Home-page: https://github.com/TransposeData/transpose-python-sdk
Author: Michael Calvey (michaeljohncalvey), Alex Langshur (alangshur), Jonathan Becker (jon-becker), Patrick Croke (tannishmango)
Author-email: michael@transpose.io, alex@transpose.io, jon@transpose.io, patrick@transpose.io
License: MIT
Keywords: web3,data,ethereum,web3 data,ethereum data
Classifier: Development Status :: 3 - Alpha
Classifier: Intended Audience :: Developers
Classifier: Intended Audience :: Information Technology
Classifier: License :: OSI Approved :: MIT License
Classifier: Natural Language :: English
Classifier: Topic :: Database
Classifier: Topic :: Utilities
License-File: LICENSE
Requires-Dist: requests
Requires-Dist: pandas
Requires-Dist: python-dotenv
